spd3303c/__init__.py
spd3303c/cli.py
spd3303c-1.0.0.dist-info/LICENSE
spd3303c-1.0.0.dist-info/METADATA
spd3303c-1.0.0.dist-info/WHEEL
spd3303c-1.0.0.dist-info/entry_points.txt
spd3303c-1.0.0.dist-info/top_level.txt
spd3303c-1.0.0.dist-info/RECORD
