Metadata-Version: 2.1
Name: spd3303c
Version: 1.0.0
Summary: Python API for SigLent SPD3303X/E/C power supplies.
Author: Kai Geissdoerfer
Author-email: kai.geissdoerfer@tu-dresden.de
License: MIT
Classifier: Development Status :: 5 - Production/Stable
Classifier: Intended Audience :: Developers
Classifier: Intended Audience :: Information Technology
Classifier: Programming Language :: Python :: 3
License-File: LICENSE
Requires-Dist: numpy
Requires-Dist: pyvisa-py
Requires-Dist: click
Requires-Dist: python-vxi11
Requires-Dist: zeroconf
Requires-Dist: psutil
